{
  "timestamp": "2025-09-17T01:57:24.096Z",
  "duration": 8845,
  "parallelWorkers": 10,
  "results": [
    {
      "task": "CSS Optimization",
      "successful": 20,
      "total": 20
    },
    {
      "task": "JavaScript Optimization",
      "successful": 20,
      "total": 20
    },
    {
      "task": "HTML Optimization",
      "successful": 70,
      "total": 70
    },
    {
      "task": "Sitemap Generation",
      "successful": 1,
      "total": 1
    },
    {
      "task": "Image Optimization",
      "successful": 1,
      "total": 1
    },
    {
      "task": "Build Validation",
      "successful": 1,
      "total": 1
    }
  ],
  "overallSuccess": true
}